{
    "date": "2024-12-26",
    "signals": {
        "VOO": {
            "date": "2024-12-24",
            "signal": "HOLD",
            "close_price": 552.8200073242188,
            "ma_short": 543.2108868538065,
            "ma_long": 540.7486647221081,
            "rsi": 53.44311561003752,
            "volatility": 0.007943928019984987,
            "indicators": {
                "ma_cross": "BULLISH",
                "rsi_status": "NEUTRAL",
                "volatility_status": "LOW"
            },
            "plots": null
        },
        "SSO": {
            "date": "2024-12-24",
            "signal": "HOLD",
            "close_price": 97.5,
            "ma_short": 94.91806582187084,
            "ma_long": 94.20435681259423,
            "rsi": 51.9155901326853,
            "volatility": 0.015785928149827554,
            "indicators": {
                "ma_cross": "BULLISH",
                "rsi_status": "NEUTRAL",
                "volatility_status": "LOW"
            },
            "plots": null
        },
        "UPRO": {
            "date": "2024-12-24",
            "signal": "HOLD",
            "close_price": 95.9800033569336,
            "ma_short": 92.63803733663356,
            "ma_long": 91.67616713674445,
            "rsi": 51.3636007473407,
            "volatility": 0.023956115851811486,
            "indicators": {
                "ma_cross": "BULLISH",
                "rsi_status": "NEUTRAL",
                "volatility_status": "LOW"
            },
            "plots": null
        },
        "QQQ": {
            "date": "2024-12-24",
            "signal": "HOLD",
            "close_price": 529.9600219726562,
            "ma_short": 508.55457516934007,
            "ma_long": 505.30689493815106,
            "rsi": 56.956787569246735,
            "volatility": 0.011567222952285725,
            "indicators": {
                "ma_cross": "BULLISH",
                "rsi_status": "NEUTRAL",
                "volatility_status": "LOW"
            },
            "plots": null
        },
        "QLD": {
            "date": "2024-12-24",
            "signal": "HOLD",
            "close_price": 116.54000091552734,
            "ma_short": 108.3320755654193,
            "ma_long": 107.14160423948054,
            "rsi": 55.87216986937653,
            "volatility": 0.0231864128147367,
            "indicators": {
                "ma_cross": "BULLISH",
                "rsi_status": "NEUTRAL",
                "volatility_status": "LOW"
            },
            "plots": null
        },
        "TQQQ": {
            "date": "2024-12-24",
            "signal": "HOLD",
            "close_price": 88.44000244140625,
            "ma_short": 79.95783866719997,
            "ma_long": 78.74353308426707,
            "rsi": 55.30754546154651,
            "volatility": 0.03459263248243715,
            "indicators": {
                "ma_cross": "BULLISH",
                "rsi_status": "NEUTRAL",
                "volatility_status": "LOW"
            },
            "plots": null
        },
        "SOXL": {
            "date": "2024-12-24",
            "signal": "SELL",
            "close_price": 30.479999542236328,
            "ma_short": 30.681089604154547,
            "ma_long": 31.78220842595686,
            "rsi": 48.5611342711456,
            "volatility": 0.05405594523343664,
            "indicators": {
                "ma_cross": "BEARISH",
                "rsi_status": "NEUTRAL",
                "volatility_status": "LOW"
            },
            "plots": null
        }
    },
    "summary": "### Market Sentiment Summary\nAs of December 24, 2024, the overall market sentiment is cautiously optimistic for most ETFs with a bullish short-term moving average crossover signaling potential upward momentum. However, the semiconductor-focused SOXL ETF is showing signs of weakness and a negative movement trend, indicating potential bearish sentiment for that sector.\n\n### Specific Recommendations for Each ETF\n\n1. **VOO (Vanguard S&P 500 ETF)**\n   - **Signal**: HOLD\n   - **Recommendation**: Maintain current holdings. The bullish trend indicated by moving averages and a neutral RSI suggests stability, while low volatility indicates a less turbulent trading environment.\n   - **Key Levels to Watch**: Support around $540; resistance at $560.\n\n2. **SSO (ProShares Ultra S&P 500)**\n   - **Signal**: HOLD\n   - **Recommendation**: Continue to hold. The bullish moving average crossover and neutral RSI are consistent with a stable upward trend.\n   - **Key Levels to Watch**: Support at $94; resistance around $100.\n\n3. **UPRO (ProShares UltraPro S&P 500)**\n   - **Signal**: HOLD\n   - **Recommendation**: Hold current positions, as short-term indicators suggest a potential for gains, but remain alert to broader market movements.\n   - **Key Levels to Watch**: Support near $91; resistance at $100.\n\n4. **QQQ (Invesco QQQ Trust)**\n   - **Signal**: HOLD\n   - **Recommendation**: Maintain your position. A neutral RSI coupled with a bullish moving average indicates continued strength in tech-focused stocks.\n   - **Key Levels to Watch**: Watching for support at $505, resistance around $530.\n\n5. **QLD (ProShares Ultra QQQ)**\n   - **Signal**: HOLD\n   - **Recommendation**: Keep holding the ETF as it reflects similar bullish sentiment transpiring among tech stocks.\n   - **Key Levels to Watch**: Support at $108; resistance at $120.\n\n6. **TQQQ (ProShares UltraPro QQQ)**\n   - **Signal**: HOLD\n   - **Recommendation**: Continually hold positions, acknowledging the potential for amplified returns given its leveraged nature. The bullish signals justify this stance.\n   - **Key Levels to Watch**: Support around $79; resistance at $90.\n\n7. **SOXL (Direxion Daily Semiconductor Bull 3X Shares)**\n   - **Signal**: SELL\n   - **Recommendation**: Exit or reduce positions. The bearish moving average crossover and a RSI indicating weakness point towards declining performance.\n   - **Key Levels to Watch**: Resistance near $31; support around $29.\n\n### Risk Warnings\n- **General Market Risk**: Be mindful of the broader market volatility which can affect all ETFs.\n- **Leveraged ETF Risk**: UPRO, SSO, TQQQ, and QLD are leveraged products that can produce greater losses in bearish conditions. Consider the inherent risk and volatility associated with these ETFs before maintaining or increasing positions.\n- **Sector-Specific Risk**: SOXL's weakened position reflects the volatility and risk endemic to semiconductor stocks, which can react sharply to market changes or macroeconomic factors.\n\n### Summary\nWhile maintaining a \"HOLD\" position is appropriate for most ETFs reflecting a bullish market outlook, caution is warranted specifically with SOXL, suggesting a reevaluation of positions held in this leveraged ETF. Be attentive to the support and resistance levels as key indicators for trading decisions moving forward."
}