{
    "date": "2026-03-29",
    "signals": {
        "VOO": {
            "date": "2026-03-27",
            "signal": "SELL",
            "close_price": 582.9600219726562,
            "ma_short": 624.6629794506316,
            "ma_long": 626.4926340203536,
            "rsi": 33.909614719967664,
            "volatility": 0.009118097786782742,
            "indicators": {
                "ma_cross": "BEARISH",
                "rsi_status": "OVERSOLD",
                "volatility_status": "LOW"
            },
            "plots": null
        },
        "SSO": {
            "date": "2026-03-27",
            "signal": "SELL",
            "close_price": 49.380001068115234,
            "ma_short": 56.91978714313913,
            "ma_long": 57.33543857775236,
            "rsi": 33.4849172026271,
            "volatility": 0.01780558657030002,
            "indicators": {
                "ma_cross": "BEARISH",
                "rsi_status": "OVERSOLD",
                "volatility_status": "LOW"
            },
            "plots": null
        },
        "UPRO": {
            "date": "2026-03-27",
            "signal": "SELL",
            "close_price": 90.20999908447266,
            "ma_short": 112.20872286532787,
            "ma_long": 113.53964875873767,
            "rsi": 33.414001030142416,
            "volatility": 0.026686152776416065,
            "indicators": {
                "ma_cross": "BEARISH",
                "rsi_status": "OVERSOLD",
                "volatility_status": "LOW"
            },
            "plots": null
        },
        "QQQ": {
            "date": "2026-03-27",
            "signal": "SELL",
            "close_price": 562.5800170898438,
            "ma_short": 605.7957439016789,
            "ma_long": 608.6143852367736,
            "rsi": 38.02511110120242,
            "volatility": 0.011484944081316905,
            "indicators": {
                "ma_cross": "BEARISH",
                "rsi_status": "NEUTRAL",
                "volatility_status": "LOW"
            },
            "plots": null
        },
        "QLD": {
            "date": "2026-03-27",
            "signal": "SELL",
            "close_price": 58.04999923706055,
            "ma_short": 67.76340468386387,
            "ma_long": 68.50894767359684,
            "rsi": 37.74523966756597,
            "volatility": 0.02293129540576265,
            "indicators": {
                "ma_cross": "BEARISH",
                "rsi_status": "OVERSOLD",
                "volatility_status": "LOW"
            },
            "plots": null
        },
        "TQQQ": {
            "date": "2026-03-27",
            "signal": "SELL",
            "close_price": 38.779998779296875,
            "ma_short": 49.39787235665828,
            "ma_long": 50.287719191166396,
            "rsi": 37.53536961840067,
            "volatility": 0.03440211499401124,
            "indicators": {
                "ma_cross": "BEARISH",
                "rsi_status": "OVERSOLD",
                "volatility_status": "LOW"
            },
            "plots": null
        },
        "SOXL": {
            "date": "2026-03-27",
            "signal": "HOLD",
            "close_price": 46.61000061035156,
            "ma_short": 59.608510281177274,
            "ma_long": 58.848596271715664,
            "rsi": 39.197311064767156,
            "volatility": 0.06580281051279531,
            "indicators": {
                "ma_cross": "BULLISH",
                "rsi_status": "NEUTRAL",
                "volatility_status": "LOW"
            },
            "plots": null
        }
    },
    "summary": "### Overall Market Sentiment\nThe current market sentiment is bearish across most major ETFs and leveraged ETFs analyzed. The trading signals indicate a strong sell sentiment, characterized by predominant bearish moving average crosses and oversold Relative Strength Index (RSI) values. Notably, volatility is low, suggesting that while price movement may not be drastic, the trend is more likely to continue downwards.\n\n### Specific Recommendations\n1. **VOO (Vanguard S&P 500 ETF)**:\n   - **Action**: SELL\n   - **Rationale**: Bearish moving average crossover, low RSI indicating oversold conditions, and share price below both short and long-term moving averages suggest it is prudent to exit positions.\n\n2. **SSO (ProShares Ultra S&P500)**:\n   - **Action**: SELL\n   - **Rationale**: Similar to VOO, the bearish signals indicate a likelihood of further declines. Exiting positions is recommended as the leveraged structure increases risk.\n\n3. **UPRO (ProShares UltraPro S&P500)**:\n   - **Action**: SELL\n   - **Rationale**: The bearish indicators and oversold RSI recommend taking losses now to avoid potentially larger declines. Given its leveraged nature, caution is warranted.\n\n4. **QQQ (Invesco QQQ ETF)**:\n   - **Action**: SELL\n   - **Rationale**: The ETF shows bearish sentiment. Exit positions to avoid potential further losses as it trades below moving averages and the moving average crossover is bearish.\n\n5. **QLD (ProShares Ultra QQQ)**:\n   - **Action**: SELL\n   - **Rationale**: The leveraged ETF mirrors QQQ's bearish scenario. Market dynamics suggest exiting before additional downturns.\n\n6. **TQQQ (ProShares UltraPro QQQ)**:\n   - **Action**: SELL\n   - **Rationale**: Given strong sell signals and bearish indicators, exiting this leveraged ETF position is advised.\n\n7. **SOXL (Direxion Daily Semiconductor Bull 3X Shares)**:\n   - **Action**: HOLD\n   - **Rationale**: While it has a bullish moving average crossover, other indicators show a neutral RSI. Currently, maintaining this position may be prudent unless bearish sentiment continues to develop.\n\n### Risk Warnings\n- **Leveraged ETFs**: The leveraged ETFs (SSO, UPRO, QLD, TQQQ) amplify both gains and losses. Given the strong sell signals, holding these may result in disproportionately large losses during a downturn.\n- **Market Volatility**: Although current volatility is low, sudden shifts can lead to unexpected price movements, especially in leveraged products, increasing the need for tight risk management.\n- **Market Dynamics**: The overall market may remain under pressure due to economic uncertainties or external shocks; staying informed is crucial.\n\n### Key Levels to Watch\n1. **Support Levels**: Monitor for potential support levels around recent lows\u2014if these break, it indicates further downside risk.\n2. **Resistance Levels**: Be aware of any rally attempts hitting moving averages (e.g., VOO's 624 and 626 levels for short/long MA) as resistance might confirm further downside.\n3. **Oversold Conditions**: While RSI is currently low, watch for any rebound or divergence patterns which might suggest an upcoming reversal. \n\nIn summary, the analysis indicates a clear recommendation to sell most positions while adopting a cautious stance with SOXL. Continuous monitoring of key levels and market dynamics is essential to navigate this bearish environment effectively."
}