{
    "date": "2025-03-22",
    "signals": {
        "VOO": {
            "date": "2025-03-21",
            "signal": "HOLD",
            "close_price": 520.260009765625,
            "ma_short": 543.0436161122424,
            "ma_long": 542.6557900947437,
            "rsi": 38.45433405111551,
            "volatility": 0.011277819408286722,
            "indicators": {
                "ma_cross": "BULLISH",
                "rsi_status": "NEUTRAL",
                "volatility_status": "LOW"
            },
            "plots": null
        },
        "SSO": {
            "date": "2025-03-21",
            "signal": "SELL",
            "close_price": 84.58999633789062,
            "ma_short": 93.08255313305145,
            "ma_long": 93.0849120826052,
            "rsi": 37.11115315548563,
            "volatility": 0.022332204875368675,
            "indicators": {
                "ma_cross": "BEARISH",
                "rsi_status": "OVERSOLD",
                "volatility_status": "LOW"
            },
            "plots": null
        },
        "UPRO": {
            "date": "2025-03-21",
            "signal": "SELL",
            "close_price": 76.5,
            "ma_short": 88.97680826390044,
            "ma_long": 89.05421032821923,
            "rsi": 36.56230681144703,
            "volatility": 0.03338150601381316,
            "indicators": {
                "ma_cross": "BEARISH",
                "rsi_status": "OVERSOLD",
                "volatility_status": "LOW"
            },
            "plots": null
        },
        "QQQ": {
            "date": "2025-03-21",
            "signal": "SELL",
            "close_price": 480.8399963378906,
            "ma_short": 510.6265960044049,
            "ma_long": 511.32280744586075,
            "rsi": 37.73465240426705,
            "volatility": 0.015212679307615488,
            "indicators": {
                "ma_cross": "BEARISH",
                "rsi_status": "OVERSOLD",
                "volatility_status": "LOW"
            },
            "plots": null
        },
        "QLD": {
            "date": "2025-03-21",
            "signal": "SELL",
            "close_price": 93.55999755859375,
            "ma_short": 106.84468127311544,
            "ma_long": 107.32140390496505,
            "rsi": 36.68528678860218,
            "volatility": 0.03007835821112462,
            "indicators": {
                "ma_cross": "BEARISH",
                "rsi_status": "OVERSOLD",
                "volatility_status": "LOW"
            },
            "plots": null
        },
        "TQQQ": {
            "date": "2025-03-21",
            "signal": "SELL",
            "close_price": 62.18000030517578,
            "ma_short": 76.99957478300054,
            "ma_long": 77.62157928734494,
            "rsi": 35.97652683646881,
            "volatility": 0.0449709275288884,
            "indicators": {
                "ma_cross": "BEARISH",
                "rsi_status": "OVERSOLD",
                "volatility_status": "LOW"
            },
            "plots": null
        },
        "SOXL": {
            "date": "2025-03-21",
            "signal": "SELL",
            "close_price": 19.280000686645508,
            "ma_short": 25.527872410226376,
            "ma_long": 26.17491236904211,
            "rsi": 40.32921935597236,
            "volatility": 0.0692321999608856,
            "indicators": {
                "ma_cross": "BEARISH",
                "rsi_status": "NEUTRAL",
                "volatility_status": "LOW"
            },
            "plots": null
        }
    },
    "summary": "### Market Sentiment\nOverall market sentiment is currently bearish, as indicated by the signals from multiple ETFs, particularly the leveraged ETFs which typically amplify underlying market trends. The majority of the analyzed securities are exhibiting \"SELL\" signals with key indicators suggesting oversold conditions and bearish moving average crossovers. The low volatility across these securities suggests the potential for minor fluctuations, but overall downward momentum appears to be dominant.\n\n### ETF-Specific Recommendations\n\n1. **VOO (Vanguard S&P 500 ETF)**\n   - **Action**: Hold\n   - **Comments**: Despite the bearish environment, VOO's signals show a neutral RSI and a bullish MA cross, suggesting potential stabilization. Observe closely for momentum shifts before considering new positions.\n\n2. **SSO (ProShares Ultra S&P 500)**\n   - **Action**: Sell\n   - **Comments**: Negative indicators across the board, including strong bearish signals. The oversold RSI hints at possible short-term rebound opportunities; however, selling is advised to minimize exposure.\n\n3. **UPRO (ProShares UltraPro S&P 500)**\n   - **Action**: Sell\n   - **Comments**: Similar to SSO, UPRO is showing bearish signals with an oversold RSI. The leverage increases risk\u2014closing positions may limit potential losses during downturns.\n\n4. **QQQ (Invesco QQQ Trust)**\n   - **Action**: Sell\n   - **Comments**: QQQ's indicators continue to show bearish patterns with no immediate signs of reversal. Selling is recommended to avoid further exposure to tech sector volatility.\n\n5. **QLD (ProShares Ultra QQQ)**\n   - **Action**: Sell\n   - **Comments**: QLD is under similar bearish pressure as QQQ. Exit positions to mitigate risk, as leverage can exacerbate losses in declining markets.\n\n6. **TQQQ (ProShares UltraPro QQQ)**\n   - **Action**: Sell\n   - **Comments**: With strong bearish signals and oversold conditions, TQQQ's leveraged nature heightens the risk. Exiting now is prudent.\n\n7. **SOXL (Direxion Daily Semiconductor Bull 3X Shares)**\n   - **Action**: Sell\n   - **Comments**: SOXL shows some resilience with a higher RSI than others, but it remains in a bearish posture. The leveraged nature increases risk exposure; sell to avoid potential large losses.\n\n### Risk Warnings\nGiven the prevailing bear market conditions, investors should be cautious of the heightened volatility associated with leveraged ETFs. Each of these securities can exhibit amplified movements in response to market shifts, leading to more significant gains or losses. Carefully managing positions in light of this volatility is crucial.\n\n### Key Levels to Watch\n- **VOO**: Watch for resistance at the MA short of 543.04; support is important to monitor around recent low close prices.\n- **SSO, UPRO, QQQ, QLD, TQQQ**: Watch the resistance levels around the moving averages (around the 93-94 range for SSO and 88-89 for UPRO). They may offer potential exit points for existing holdings.\n- **SOXL**: Monitor the MA short of 25.53 for a potential reversal signal. \n\nInvestors should remain vigilant and closely monitor market trends, as conditions can change rapidly, especially with leveraged ETFs involved."
}