{
    "date": "2025-09-23",
    "signals": {
        "VOO": {
            "date": "2025-09-22",
            "signal": "HOLD",
            "close_price": 614.760009765625,
            "ma_short": 590.8059627451795,
            "ma_long": 587.654386821546,
            "rsi": 70.27102270354543,
            "volatility": 0.004987436852850911,
            "indicators": {
                "ma_cross": "BULLISH",
                "rsi_status": "NEUTRAL",
                "volatility_status": "LOW"
            },
            "plots": null
        },
        "SSO": {
            "date": "2025-09-22",
            "signal": "HOLD",
            "close_price": 112.70999908447266,
            "ma_short": 104.76000051295503,
            "ma_long": 103.78368471379866,
            "rsi": 68.761691699343,
            "volatility": 0.01003751039683479,
            "indicators": {
                "ma_cross": "BULLISH",
                "rsi_status": "NEUTRAL",
                "volatility_status": "LOW"
            },
            "plots": null
        },
        "UPRO": {
            "date": "2025-09-22",
            "signal": "HOLD",
            "close_price": 112.38999938964844,
            "ma_short": 101.05382943660655,
            "ma_long": 99.72017522443805,
            "rsi": 68.47264353480949,
            "volatility": 0.015000602350604622,
            "indicators": {
                "ma_cross": "BULLISH",
                "rsi_status": "NEUTRAL",
                "volatility_status": "LOW"
            },
            "plots": null
        },
        "QQQ": {
            "date": "2025-09-22",
            "signal": "HOLD",
            "close_price": 602.2000122070312,
            "ma_short": 573.8489379882812,
            "ma_long": 570.4984227230674,
            "rsi": 65.7711125585508,
            "volatility": 0.006600797577766468,
            "indicators": {
                "ma_cross": "BULLISH",
                "rsi_status": "NEUTRAL",
                "volatility_status": "LOW"
            },
            "plots": null
        },
        "QLD": {
            "date": "2025-09-22",
            "signal": "HOLD",
            "close_price": 138.30999755859375,
            "ma_short": 126.1325537498961,
            "ma_long": 124.84368454782586,
            "rsi": 65.15627403248897,
            "volatility": 0.013300761730695762,
            "indicators": {
                "ma_cross": "BULLISH",
                "rsi_status": "NEUTRAL",
                "volatility_status": "LOW"
            },
            "plots": null
        },
        "TQQQ": {
            "date": "2025-09-22",
            "signal": "HOLD",
            "close_price": 104.72000122070312,
            "ma_short": 91.59191440014129,
            "ma_long": 90.27052588211863,
            "rsi": 64.94522886561504,
            "volatility": 0.019848398658247498,
            "indicators": {
                "ma_cross": "BULLISH",
                "rsi_status": "NEUTRAL",
                "volatility_status": "LOW"
            },
            "plots": null
        },
        "SOXL": {
            "date": "2025-09-22",
            "signal": "HOLD",
            "close_price": 34.43000030517578,
            "ma_short": 27.36021285361432,
            "ma_long": 27.225965031406336,
            "rsi": 66.90950743017554,
            "volatility": 0.04021361733462796,
            "indicators": {
                "ma_cross": "BULLISH",
                "rsi_status": "NEUTRAL",
                "volatility_status": "LOW"
            },
            "plots": null
        }
    },
    "summary": "### Current Market Analysis (as of September 22, 2025)\n\n#### 1. Overall Market Sentiment:\nThe current market sentiment is generally bullish, as indicated by the \u201cHOLD\u201d signals across several ETFs including VOO, SSO, UPRO, QQQ, QLD, TQQQ, and SOXL. All assets are trading above their short and long moving averages, suggesting a strong upward trend. The RSI values indicate that most ETFs are approaching the overbought region but have not yet surpassed the critical threshold (typically 70), suggesting that while the market is strong, there may still be room for continued upward movement.\n\n#### 2. Specific Recommendations for Each ETF:\n- **VOO (S&P 500 ETF)**: **HOLD**\n  - Strength in moving averages and neutral RSI suggests maintaining position. \n  - Watch for a sustained push above 615 for further bullish confirmation.\n\n- **SSO (ProShares Ultra S&P500)**: **HOLD**\n  - Continue holding as the bullish cross and RSI show momentum. \n  - Key level to monitor is 115. A breakout here could signal further gains.\n\n- **UPRO (ProShares UltraPro S&P500)**: **HOLD**\n  - In line with the bullish signals. Maintain position as the ETF is well above key moving averages.\n  - Watch for breakouts above 115.\n\n- **QQQ (Invesco QQQ Trust)**: **HOLD**\n  - Maintain position; RSI is strong but not overbought yet. \n  - Key level at 605 should be observed for potential upward momentum.\n\n- **QLD (ProShares Ultra QQQ)**: **HOLD**\n  - Bullish indicators suggest retaining holdings. \n  - Monitor for potential breakout above 140.\n\n- **TQQQ (ProShares UltraPro QQQ)**: **HOLD**\n  - Position remains solid with sufficient upwards momentum. \n  - Keep an eye on 105 as a potential breakout level.\n\n- **SOXL (Direxion Daily Semiconductor Bull 3X Shares)**: **HOLD**\n  - Strong bullish indicators continue to affirm the position. \n  - Watch for resistance around 36, as this could impact the continuation of bullish momentum.\n\n#### 3. Risk Warnings:\n- **Overbought Conditions**: The RSI values across many ETFs are approaching 70, which indicates potential overbought conditions. Traders should be cautious, as reversals could occur if buying momentum wanes.\n- **High Volatility**: Although most ETFs are reporting low volatility, SOXL in particular has higher volatility, indicating an elevated risk profile. Be prepared for rapid price swings.\n- **Market Sentiment Changes**: Sudden changes in macroeconomic indicators or geopolitical events can shift the market sentiment rapidly. Regular monitoring is necessary.\n\n#### 4. Key Levels to Watch:\n- **VOO**: Key resistance at 615.\n- **SSO**: Focus on 115 for bullish confirmation.\n- **UPRO**: Watch for breakout at 115.\n- **QQQ**: Monitor 605.\n- **QLD**: Key level at 140 for potential upward movement.\n- **TQQQ**: Important breakout level is 105.\n- **SOXL**: Watch for resistance near 36, as a failure to break this level could trigger a pullback.\n\n### Conclusion:\nAll analyzed ETFs currently reflect bullish sentiment with the majority maintaining a \"HOLD\" position. Investors should remain vigilant about overbought conditions and potential changing market dynamics, but stay invested as long as support levels hold."
}