{
    "date": "2026-03-07",
    "signals": {
        "VOO": {
            "date": "2026-03-06",
            "signal": "HOLD",
            "close_price": 618.4299926757812,
            "ma_short": 632.6946826691324,
            "ma_long": 631.6151679858826,
            "rsi": 43.11394143436037,
            "volatility": 0.007782634053473074,
            "indicators": {
                "ma_cross": "BULLISH",
                "rsi_status": "NEUTRAL",
                "volatility_status": "LOW"
            },
            "plots": null
        },
        "SSO": {
            "date": "2026-03-06",
            "signal": "HOLD",
            "close_price": 55.619998931884766,
            "ma_short": 58.61340421311399,
            "ma_long": 58.49481897186815,
            "rsi": 42.023340527945905,
            "volatility": 0.01553640289792063,
            "indicators": {
                "ma_cross": "BULLISH",
                "rsi_status": "NEUTRAL",
                "volatility_status": "LOW"
            },
            "plots": null
        },
        "UPRO": {
            "date": "2026-03-06",
            "signal": "HOLD",
            "close_price": 108.16000366210938,
            "ma_short": 117.47191473778258,
            "ma_long": 117.20488069768538,
            "rsi": 41.62038805985774,
            "volatility": 0.02319415641990115,
            "indicators": {
                "ma_cross": "BULLISH",
                "rsi_status": "NEUTRAL",
                "volatility_status": "LOW"
            },
            "plots": null
        },
        "QQQ": {
            "date": "2026-03-06",
            "signal": "HOLD",
            "close_price": 599.75,
            "ma_short": 614.7382955348238,
            "ma_long": 614.729950486568,
            "rsi": 42.957024261342795,
            "volatility": 0.011099110834781175,
            "indicators": {
                "ma_cross": "BULLISH",
                "rsi_status": "NEUTRAL",
                "volatility_status": "LOW"
            },
            "plots": null
        },
        "QLD": {
            "date": "2026-03-06",
            "signal": "SELL",
            "close_price": 66.19000244140625,
            "ma_short": 70.07276608081574,
            "ma_long": 70.17757067764015,
            "rsi": 41.950550636739884,
            "volatility": 0.02199635527226279,
            "indicators": {
                "ma_cross": "BEARISH",
                "rsi_status": "NEUTRAL",
                "volatility_status": "LOW"
            },
            "plots": null
        },
        "TQQQ": {
            "date": "2026-03-06",
            "signal": "SELL",
            "close_price": 47.540000915527344,
            "ma_short": 52.120850989159116,
            "ma_long": 52.29038666842277,
            "rsi": 41.50521716151128,
            "volatility": 0.03290373053164976,
            "indicators": {
                "ma_cross": "BEARISH",
                "rsi_status": "NEUTRAL",
                "volatility_status": "LOW"
            },
            "plots": null
        },
        "SOXL": {
            "date": "2026-03-06",
            "signal": "HOLD",
            "close_price": 47.88999938964844,
            "ma_short": 59.27851039805311,
            "ma_long": 56.16070155093544,
            "rsi": 43.157999902985836,
            "volatility": 0.07366678537275123,
            "indicators": {
                "ma_cross": "BULLISH",
                "rsi_status": "NEUTRAL",
                "volatility_status": "LOW"
            },
            "plots": null
        }
    },
    "summary": "### 1. Overall Market Sentiment:\nThe current analysis suggests a mixed but cautious market sentiment. Most ETFs indicate a \"HOLD\" signal, reflecting a lack of strong bullish momentum, while two leveraged ETFs (QLD and TQQQ) are signaling \"SELL.\" The RSI levels across the board are in the neutral range, with low volatility indicating a lack of market conviction either way. The bullish trend from the moving average crossover suggests a potential for upward movement; however, the declining prices relative to the short-term moving averages signal caution.\n\n### 2. Specific Recommendations for Each ETF:\n\n- **VOO (Vanguard S&P 500 ETF)**\n  - **Signal**: HOLD\n  - **Recommendation**: Maintain position; consider watching for a break above the short-term moving average around $632. This could indicate stronger bullish momentum.\n\n- **SSO (ProShares Ultra S&P500)**\n  - **Signal**: HOLD\n  - **Recommendation**: Hold steady; watch for price recovery towards the moving averages. Strength above $58 could signal a potential buying opportunity.\n\n- **UPRO (ProShares UltraPro S&P500)**\n  - **Signal**: HOLD\n  - **Recommendation**: Retain position; observe for upward movement. A close above $117 might provide a clearer bullish signal.\n\n- **QQQ (Invesco QQQ ETF)**\n  - **Signal**: HOLD\n  - **Recommendation**: Keep the position intact; focus on upward momentum towards $614.738. A successful breach of this level could be significant.\n\n- **QLD (ProShares Ultra QQQ)**\n  - **Signal**: SELL\n  - **Recommendation**: Consider exiting the position as it shows a bearish trend with the price below moving averages. Avoid entering until a clearer bullish trend is established.\n\n- **TQQQ (ProShares UltraPro QQQ)**\n  - **Signal**: SELL\n  - **Recommendation**: Exit the position; the price action shows strong bearish signals. Wait for confirmation of a market reversal before considering re-entry.\n\n- **SOXL (Direxion Daily Semiconductor Bull 3X Shares)**\n  - **Signal**: HOLD\n  - **Recommendation**: Maintain the current position, but be alert to price movements. A close above the short-term moving average at approximately $59.28 may be a bullish indicator.\n\n### 3. Risk Warnings if Applicable:\n- The leveraged ETFs (QLD and TQQQ) are signaling \"SELL,\" indicating potential risk if held further. The underlying asset volatility is higher in these instruments; hence, they tend not only to amplify gains but also losses.\n- Low RSI levels and bearish movements suggest further downside risk. Investors should be wary of volatility spikes that may result from negative market reactions or mismatched expectations.\n\n### 4. Key Levels to Watch:\n- **VOO**: Watch for $632 (short-term MA) for potential bullish confirmation.\n- **SSO/UPRO**: Keep an eye on $58 (SSO) and $117 (UPRO); levels above these could indicate renewed bullish sentiment.\n- **QQQ**: The key level to monitor is around $614.73; it could signal momentum if broken.\n- **QLD/TQQQ**: Watch for resistance at their moving averages ($70.07 for QLD and $52.12 for TQQQ), which, if not reclaimed, may support the sell signals.\n- **SOXL**: Watch for resistance around $59.28 for potential bullish confirmation.\n\nIn summary, while maintaining positions in most ETFs seems sensible, caution is warranted, especially with leveraged ETFs as the current market scenario tilts toward cautiousness despite some bullish indicators."
}