{
    "date": "2026-06-06",
    "signals": {
        "VOO": {
            "date": "2026-06-05",
            "signal": "HOLD",
            "close_price": 678.0,
            "ma_short": 660.4123366335605,
            "ma_long": 649.5683904279742,
            "rsi": 59.7084768734908,
            "volatility": 0.007881860346311607,
            "indicators": {
                "ma_cross": "BULLISH",
                "rsi_status": "NEUTRAL",
                "volatility_status": "LOW"
            },
            "plots": null
        },
        "SSO": {
            "date": "2026-06-05",
            "signal": "HOLD",
            "close_price": 65.86000061035156,
            "ma_short": 63.0036172258093,
            "ma_long": 61.10397820723684,
            "rsi": 58.4765423734099,
            "volatility": 0.015711242165249807,
            "indicators": {
                "ma_cross": "BULLISH",
                "rsi_status": "NEUTRAL",
                "volatility_status": "LOW"
            },
            "plots": null
        },
        "UPRO": {
            "date": "2026-06-05",
            "signal": "HOLD",
            "close_price": 137.52999877929688,
            "ma_short": 129.58234048396983,
            "ma_long": 124.06491356565242,
            "rsi": 57.75913014106631,
            "volatility": 0.023662661298046127,
            "indicators": {
                "ma_cross": "BULLISH",
                "rsi_status": "NEUTRAL",
                "volatility_status": "LOW"
            },
            "plots": null
        },
        "QQQ": {
            "date": "2026-06-05",
            "signal": "HOLD",
            "close_price": 705.0599975585938,
            "ma_short": 674.3789348196476,
            "ma_long": 658.2554599695038,
            "rsi": 60.7677052947273,
            "volatility": 0.013538611775727601,
            "indicators": {
                "ma_cross": "BULLISH",
                "rsi_status": "NEUTRAL",
                "volatility_status": "LOW"
            },
            "plots": null
        },
        "QLD": {
            "date": "2026-06-05",
            "signal": "HOLD",
            "close_price": 89.54000091552734,
            "ma_short": 83.02340430401742,
            "ma_long": 79.39947650307103,
            "rsi": 59.56003615178606,
            "volatility": 0.02693822242560256,
            "indicators": {
                "ma_cross": "BULLISH",
                "rsi_status": "NEUTRAL",
                "volatility_status": "LOW"
            },
            "plots": null
        },
        "TQQQ": {
            "date": "2026-06-05",
            "signal": "HOLD",
            "close_price": 73.05000305175781,
            "ma_short": 66.2202125711644,
            "ma_long": 62.2002157244766,
            "rsi": 58.67372536130652,
            "volatility": 0.04030662836947677,
            "indicators": {
                "ma_cross": "BULLISH",
                "rsi_status": "NEUTRAL",
                "volatility_status": "LOW"
            },
            "plots": null
        },
        "SOXL": {
            "date": "2026-06-05",
            "signal": "HOLD",
            "close_price": 182.5399932861328,
            "ma_short": 142.25319200880983,
            "ma_long": 126.35245654457493,
            "rsi": 56.13598107719613,
            "volatility": 0.10853291298313456,
            "indicators": {
                "ma_cross": "BULLISH",
                "rsi_status": "NEUTRAL",
                "volatility_status": "LOW"
            },
            "plots": null
        }
    },
    "summary": "### Market Overview\n\nAs of June 5, 2026, the overall market sentiment appears to be cautiously optimistic. The signals from the core ETFs and their leveraged counterparts suggest a prevailing bullish trend, evidenced by bullish moving average crosses in all cases. However, the Relative Strength Index (RSI) figures are neutral, indicating that while the market is not overbought, there is also no immediate momentum suggesting a significant uptrend. Volatility across the ETFs is currently low, which may imply stable market conditions, but it also indicates a potential for sudden price shifts if market sentiment changes.\n\n### Specific Recommendations for Each ETF\n\n1. **VOO (Vanguard S&P 500 ETF)**  \n   - **Recommendation:** Hold  \n   - **Rationale:** The ETF is above both its short and long moving averages, suggesting a stable position. With the RSI at 59.71, there's room for upward movement, but a cautious approach is warranted.\n\n2. **SSO (ProShares Ultra S&P500)**  \n   - **Recommendation:** Hold  \n   - **Rationale:** Similar to VOO, SSO shows positive moving averages but remains at a neutral RSI. This leveraged ETF can amplify gains in a rising market, so monitoring is necessary for upscale movement.\n\n3. **UPRO (ProShares UltraPro S&P500)**  \n   - **Recommendation:** Hold  \n   - **Rationale:** UPRO's setup is bullish, with its price well above moving averages. As a leveraged ETF, it can offer significant returns, but the neutral RSI suggests avoiding aggressive buying just yet.\n\n4. **QQQ (Invesco QQQ ETF)**  \n   - **Recommendation:** Hold  \n   - **Rationale:** QQQ has strong bullish indicators and a strong price point in the tech sector, but similarly to others, it should be monitored for any volatility shifts before taking new positions.\n\n5. **QLD (ProShares Ultra QQQ)**  \n   - **Recommendation:** Hold  \n   - **Rationale:** QLD mirrors QQQ with bullish signals. The low volatility is encouraging, but as a leveraged ETF, it may be susceptible to sharper moves; careful market watching is advised.\n\n6. **TQQQ (ProShares UltraPro QQQ)**  \n   - **Recommendation:** Hold  \n   - **Rationale:** TQQQ is also bullish and offers potential for high returns, but with low momentum (RSI of 58.67), a hold is prudent until a strong uptrend is established.\n\n7. **SOXL (Direxion Daily Semiconductor Bull 3X Shares)**  \n   - **Recommendation:** Hold  \n   - **Rationale:** Although SOXL is part of a bullish trend with significant growth potential, the high volatility compared to others makes it a risky proposition. Caution is advised before increasing positions.\n\n### Risk Warnings\n\n- **Market Volatility:** While current volatility is low, conditions can change rapidly. Investors should be prepared for sudden downturns or corrections.\n- **Leveraged ETFs:** The volatility and risks associated with leveraged ETFs like SSO, UPRO, TQQQ, and SOXL mean that they can lead to amplified gains but also intensified losses.\n- **Neutral RSI Levels:** The current neutral RSI suggests that none of the ETFs are in strong momentum territory. Be cautious about entering new positions without further confirmation of a trend.\n\n### Key Levels to Watch\n\n- **VOO:** Watch for breaks above $690 for potential upward momentum.\n- **SSO:** Key resistance at $68; support around $63.\n- **UPRO:** Support is around $130, watch for the resistance near $140.\n- **QQQ:** Resistance at $710, with support at $680.\n- **QLD:** Watch for a move above $90 for bullish confirmation; support at $84.\n- **TQQQ:** Significant level at $75 resistance; watch for support around $70.\n- **SOXL:** Key resistance at $185; with a support level near $175 to manage risk.\n\n### Conclusion\n\nMaintain \"Hold\" positions across all analyzed ETFs given the current bullish signals tempered by the neutral RSI. Monitor for changing conditions and price levels for informed decision-making. Caution is warranted, particularly with leveraged products, due to their risk profile."
}