{
    "date": "2025-03-13",
    "signals": {
        "VOO": {
            "date": "2025-03-12",
            "signal": "BUY",
            "close_price": 513.760009765625,
            "ma_short": 546.403192398396,
            "ma_long": 546.1801602547629,
            "rsi": 34.49115963272966,
            "volatility": 0.010148469251689074,
            "indicators": {
                "ma_cross": "BULLISH",
                "rsi_status": "OVERSOLD",
                "volatility_status": "LOW"
            },
            "plots": null
        },
        "SSO": {
            "date": "2025-03-12",
            "signal": "SELL",
            "close_price": 82.77999877929688,
            "ma_short": 94.41851043701172,
            "ma_long": 94.49807498329564,
            "rsi": 33.572412444211594,
            "volatility": 0.02003505952856472,
            "indicators": {
                "ma_cross": "BEARISH",
                "rsi_status": "OVERSOLD",
                "volatility_status": "LOW"
            },
            "plots": null
        },
        "UPRO": {
            "date": "2025-03-12",
            "signal": "SELL",
            "close_price": 74.1500015258789,
            "ma_short": 90.9838292547997,
            "ma_long": 91.18455117208916,
            "rsi": 33.44082390576553,
            "volatility": 0.029950502410253654,
            "indicators": {
                "ma_cross": "BEARISH",
                "rsi_status": "OVERSOLD",
                "volatility_status": "LOW"
            },
            "plots": null
        },
        "QQQ": {
            "date": "2025-03-12",
            "signal": "SELL",
            "close_price": 476.9200134277344,
            "ma_short": 515.9510640895113,
            "ma_long": 516.8995270310787,
            "rsi": 35.93260208775534,
            "volatility": 0.014138776052842,
            "indicators": {
                "ma_cross": "BEARISH",
                "rsi_status": "OVERSOLD",
                "volatility_status": "LOW"
            },
            "plots": null
        },
        "QLD": {
            "date": "2025-03-12",
            "signal": "SELL",
            "close_price": 92.33000183105469,
            "ma_short": 109.32085175209858,
            "ma_long": 109.93742705228036,
            "rsi": 35.28055121177195,
            "volatility": 0.02794135869879431,
            "indicators": {
                "ma_cross": "BEARISH",
                "rsi_status": "OVERSOLD",
                "volatility_status": "LOW"
            },
            "plots": null
        },
        "TQQQ": {
            "date": "2025-03-12",
            "signal": "SELL",
            "close_price": 61.130001068115234,
            "ma_short": 79.80170245880777,
            "ma_long": 80.60439019454152,
            "rsi": 34.98213309447169,
            "volatility": 0.0417896873644786,
            "indicators": {
                "ma_cross": "BEARISH",
                "rsi_status": "OVERSOLD",
                "volatility_status": "LOW"
            },
            "plots": null
        },
        "SOXL": {
            "date": "2025-03-12",
            "signal": "SELL",
            "close_price": 18.299999237060547,
            "ma_short": 26.996383058263902,
            "ma_long": 27.309693453604716,
            "rsi": 40.18616938979559,
            "volatility": 0.06760175101063544,
            "indicators": {
                "ma_cross": "BEARISH",
                "rsi_status": "NEUTRAL",
                "volatility_status": "LOW"
            },
            "plots": null
        }
    },
    "summary": "### Market Sentiment\nOverall, the current market sentiment appears bearish based on the provided signals. Most ETFs are showing sell signals, indicating a downward trend, despite some being in oversold conditions. In particular, the leveraged ETFs are underperforming relative to their long-term averages. This suggests a challenging environment for growth, particularly in technology and broader market indices.\n\n### Specific Recommendations for Each ETF\n\n- **VOO (Vanguard S&P 500 ETF)**\n  - **Recommendation**: **BUY**. Given the current oversold RSI status and a bullish moving average crossover, this may present a potential entry point for long-term investors.\n  \n- **SSO (ProShares Ultra S&P500)**\n  - **Recommendation**: **SELL**. Maintain a bearish stance as both short-term and long-term moving averages are declining. The oversold RSI offers little comfort, indicating the potential for further losses.\n\n- **UPRO (ProShares UltraPro S&P500)**\n  - **Recommendation**: **SELL**. Similar to SSO, strong bearish trends with no signs of recovery suggest staying out of this leveraged ETF until signals stabilize.\n\n- **QQQ (Invesco QQQ Trust)**\n  - **Recommendation**: **SELL**. The current RSI is still oversold, but bearish moving average indicators suggest a continued decline. Consider reassessing once momentum shifts.\n\n- **QLD (ProShares Ultra QQQ)**\n  - **Recommendation**: **SELL**. Bearish signals are present across both averaging metrics. It's prudent to wait for stabilization before considering a position.\n\n- **TQQQ (ProShares UltraPro QQQ)**\n  - **Recommendation**: **SELL**. Continue to hold off on TQQQ\u2014similar conditions of overselling and bearish momentum suggest significant downside risk.\n\n- **SOXL (Direxion Daily Semiconductor Bull 3X Shares)**\n  - **Recommendation**: **SELL**. While the RSI is not oversold, the overall bearish trend warrants caution. The semiconductor sector remains volatile and could face further pressure.\n\n### Risk Warnings\nThe prevailing conditions indicate a high-risk environment:\n- **Volatility**: Low volatility in tandem with bearish trends suggests instability that could lead to sharp reversals. \n- **Leverage Exposure**: Holding leveraged ETFs in a downward trending market increases potential losses significantly. Caution is advised.\n- **Overall Economic Factors**: Broader economic conditions (inflation, interest rates) could further impact market performance, so keep abreast of economic indicators.\n\n### Key Levels to Watch\n- **VOO**: Watch for resistance around 546; a movement above could indicate a reversal or a re-entry point.\n- **SSO and UPRO**: Key support levels are in the 74-82 range. Breaks below could signify further declines.\n- **QQQ and QLD**: Watch the 515-516 range; a sustained break could signal more selling pressure.\n- **TQQQ**: Similar to QQQ, key resistance at the 79-80 ranges is critical; failure to breach could continue the downward trend.\n- **SOXL**: Pay attention to 27 as a major support area; a breach could lead to increased selling.\n\n### Conclusion\nIn summary, the market shows bearish indicators overall, with various ETFs providing a mix of signals. Caution is advised, particularly with leveraged ETFs, as they carry higher risks during declining phases. Monitoring key levels and market sentiment will be critical going forward, especially for those looking to incorporate some strategic positions in oversold conditions."
}