{
    "date": "2025-03-09",
    "signals": {
        "VOO": {
            "date": "2025-03-07",
            "signal": "SELL",
            "close_price": 529.510009765625,
            "ma_short": 548.2400006233378,
            "ma_long": 548.3411212051124,
            "rsi": 37.90589111378463,
            "volatility": 0.009170699141340798,
            "indicators": {
                "ma_cross": "BEARISH",
                "rsi_status": "OVERSOLD",
                "volatility_status": "LOW"
            },
            "plots": null
        },
        "SSO": {
            "date": "2025-03-07",
            "signal": "SELL",
            "close_price": 87.98999786376953,
            "ma_short": 95.12297869743185,
            "ma_long": 95.32759254857113,
            "rsi": 36.73223955493246,
            "volatility": 0.0180812970979142,
            "indicators": {
                "ma_cross": "BEARISH",
                "rsi_status": "OVERSOLD",
                "volatility_status": "LOW"
            },
            "plots": null
        },
        "UPRO": {
            "date": "2025-03-07",
            "signal": "SELL",
            "close_price": 81.38999938964844,
            "ma_short": 92.02680806910737,
            "ma_long": 92.42457473487185,
            "rsi": 36.39821678835174,
            "volatility": 0.027061437314523394,
            "indicators": {
                "ma_cross": "BEARISH",
                "rsi_status": "OVERSOLD",
                "volatility_status": "LOW"
            },
            "plots": null
        },
        "QQQ": {
            "date": "2025-03-07",
            "signal": "SELL",
            "close_price": 491.7900085449219,
            "ma_short": 518.67765905502,
            "ma_long": 519.9062264425713,
            "rsi": 37.7588025801723,
            "volatility": 0.012507833571910083,
            "indicators": {
                "ma_cross": "BEARISH",
                "rsi_status": "OVERSOLD",
                "volatility_status": "LOW"
            },
            "plots": null
        },
        "QLD": {
            "date": "2025-03-07",
            "signal": "SELL",
            "close_price": 98.36000061035156,
            "ma_short": 110.55574522627161,
            "ma_long": 111.31685089646724,
            "rsi": 36.90567016628259,
            "volatility": 0.024856082236096744,
            "indicators": {
                "ma_cross": "BEARISH",
                "rsi_status": "OVERSOLD",
                "volatility_status": "LOW"
            },
            "plots": null
        },
        "TQQQ": {
            "date": "2025-03-07",
            "signal": "SELL",
            "close_price": 67.41000366210938,
            "ma_short": 81.18468118221202,
            "ma_long": 82.17044361850671,
            "rsi": 36.42997916959309,
            "volatility": 0.03723165128566331,
            "indicators": {
                "ma_cross": "BEARISH",
                "rsi_status": "OVERSOLD",
                "volatility_status": "LOW"
            },
            "plots": null
        },
        "SOXL": {
            "date": "2025-03-07",
            "signal": "SELL",
            "close_price": 20.8799991607666,
            "ma_short": 27.66106394503979,
            "ma_long": 27.971297749301844,
            "rsi": 35.8021706590374,
            "volatility": 0.06307313265748382,
            "indicators": {
                "ma_cross": "BEARISH",
                "rsi_status": "OVERSOLD",
                "volatility_status": "LOW"
            },
            "plots": null
        }
    },
    "summary": "### Current Market Analysis\n\n#### 1. Overall Market Sentiment:\nThe overall market sentiment indicates a bearish outlook as all analyzed ETFs show \"SELL\" signals. The presence of low Relative Strength Index (RSI) values near the oversold territory suggests that these ETFs are under significant selling pressure. The moving averages also reflect bearish conditions, further confirming downward momentum across the board. The low volatility readings indicate that while the market is stable, a sudden price movement could occur, potentially leading to sharp declines.\n\n#### 2. Specific Recommendations for Each ETF:\n\n- **VOO (Vanguard S&P 500 ETF)**\n  - **Action**: Sell. Maintain cash positions until signs of recovery emerge.\n  - **Key Levels**: Watch for reversal near historical support levels to consider re-entry.\n\n- **SSO (ProShares Ultra S&P 500 ETF)**\n  - **Action**: Sell. This leveraged ETF amplifies market moves, and therefore exposure should be reduced significantly in bearish conditions.\n  - **Key Levels**: Consider monitoring for possible rebound levels to assess risk/reward for potential re-entry.\n\n- **UPRO (ProShares UltraPro S&P 500 ETF)**\n  - **Action**: Sell. Similar to SSO, the leveraged nature magnifies losses in declining markets. \n  - **Key Levels**: Look for critical support zones for potential future trades.\n\n- **QQQ (Invesco QQQ ETF)**\n  - **Action**: Sell. The tech-heavy nature of this ETF in bearish conditions suggests avoiding long positions.\n  - **Key Levels**: Watch for significant support at lower price levels for future investment decisions.\n\n- **QLD (ProShares Ultra QQQ ETF)**\n  - **Action**: Sell. Given it's a leveraged ETF, reduce exposure; consider re-evaluating on signs of bullish reversals.\n  - **Key Levels**: Monitor for resubmission levels if a recovery is signaled.\n\n- **TQQQ (ProShares UltraPro QQQ ETF)**\n  - **Action**: Sell. As with other leverage instruments, higher sensitivity to market declines warrants caution.\n  - **Key Levels**: Keep an eye on key resistance which may provide insight into the direction when considering re-entry.\n\n- **SOXL (Direxion Daily Semiconductor Bull 3X Shares)**\n  - **Action**: Sell. This repeated bearish confirmation suggests cutting losses now is prudent.\n  - **Key Levels**: Pay attention to historical support levels for potential recovery investments in the future.\n\n#### 3. Risk Warnings:\n- **Market Volatility**: Although volatility is currently low, leveraged ETFs can be especially risky in volatile market conditions. Price swings could lead to severe losses.\n- **Liquidity Risk**: In a declining market, liquidity may dry up, making it hard to execute trades at desired prices.\n- **Potential for a Short Squeeze**: As these positions are heavily sold, they could also be triggered into a short squeeze if the market unexpectedly rallies.\n\n#### 4. Key Levels to Watch:\n- **Support Levels**: Each ETF's historical support levels will be critical to monitor for potential reversals. If any of these ETFs approach these areas without a significant change in sentiment, they could be considered for entry.\n- **Resistance Levels**: Current price action relative to moving average levels will give insight into resistance areas, particularly for determining potential short entries or re-entries.\n\n### Summary\nThe current market presents a uniformly bearish scenario across multiple ETFs, particularly within the S&P 500 and NASDAQ segments. Immediate action should include selling positions, keeping a watchful eye on the respective historical support levels to identify potential future buying opportunities or to hedge current positions effectively."
}